AUTHORS.rst
CONTRIBUTING.rst
HISTORY.rst
LICENSE
MANIFEST.in
README.rst
setup.cfg
setup.py
hammer/__init__.py
hammer/exceptions.py
hammer/launch.py
hammer_variations.egg-info/PKG-INFO
hammer_variations.egg-info/SOURCES.txt
hammer_variations.egg-info/dependency_links.txt
hammer_variations.egg-info/entry_points.txt
hammer_variations.egg-info/not-zip-safe
hammer_variations.egg-info/requires.txt
hammer_variations.egg-info/top_level.txt
test/test_bayescache.py