Metadata-Version: 1.1
Name: hammer-variations
Version: 0.1.1
Summary: Hammering out the variations in deep learning models.
Home-page: https://github.com/yngtodd/hammer
Author: Todd Young
Author-email: youngmt1@ornl.gov
License: MIT
Keywords: hammer
Platform: UNKNOWN
Classifier: Development Status :: 2 - Pre-Alpha
Classifier: Intended Audience :: Developers
Classifier: License :: OSI Approved :: MIT License
Classifier: Natural Language :: English
Classifier: Programming Language :: Python :: 3.6
Classifier: Programming Language :: Python :: Implementation :: PyPy
